noisepy/__init__.py
noisepy/__main__.py
noisepy-0.1.4.2.dist-info/DESCRIPTION.rst
noisepy-0.1.4.2.dist-info/METADATA
noisepy-0.1.4.2.dist-info/RECORD
noisepy-0.1.4.2.dist-info/WHEEL
noisepy-0.1.4.2.dist-info/entry_points.txt
noisepy-0.1.4.2.dist-info/metadata.json
noisepy-0.1.4.2.dist-info/top_level.txt
noisepy-0.1.4.2.dist-info/zip-safe
